ivy_cms_unused_cleaner/__init__.py
ivy_cms_unused_cleaner/cms_cleaner.py
ivy_cms_unused_cleaner-0.0.9.dist-info/LICENSE
ivy_cms_unused_cleaner-0.0.9.dist-info/METADATA
ivy_cms_unused_cleaner-0.0.9.dist-info/WHEEL
ivy_cms_unused_cleaner-0.0.9.dist-info/top_level.txt
ivy_cms_unused_cleaner-0.0.9.dist-info/RECORD
