Metadata-Version: 2.1
Name: ivy-cms-unused-cleaner
Version: 0.0.9
Summary: Use this to remove unused CMS in your ivy project
Home-page: https://github.com/MrNocTV/ivy_unused_cms_scanner
Author: Loc Truong
Author-email: loctvuit@gmail.com
License: UNKNOWN
Platform: UNKNOWN
Classifier: Programming Language :: Python :: 3
Classifier: License :: OSI Approved :: MIT License
Classifier: Operating System :: OS Independent
Requires-Python: >=3.6
Requires-Dist: rich
